googletrans/__init__.py
googletrans_python-0.2.0.dist-info/METADATA
googletrans_python-0.2.0.dist-info/WHEEL
googletrans_python-0.2.0.dist-info/top_level.txt
googletrans_python-0.2.0.dist-info/RECORD
